{
  "project_info": {
    "project_number": "663977579940",
    "project_id": "stockhawk-eeb04"
  },
  "client": [
    {
      "client_info": {
        "mobilesdk_app_id": "1:663977579940:android:143ba334c8f86887",
        "android_client_info": {
          "package_name": "com.sam_chordas.android.stockhawk"
        }
      },
      "oauth_client": [],
      "api_key": [
        {
          "current_key": "AIzaSyAmpy1-UoD2Aal1_7NQFmeSLzADHYsaVEA"
        }
      ],
      "services": {
        "analytics_service": {
          "status": 1
        },
        "appinvite_service": {
          "status": 1,
          "other_platform_oauth_client": []
        },
        "ads_service": {
          "status": 1
        }
      }
    },
    {
      "client_info": {
        "mobilesdk_app_id": "1:663977579940:android:4097dd584dac2d8c",
        "android_client_info": {
          "package_name": "com.example.sam_chordas.stockhawk"
        }
      },
      "oauth_client": [],
      "api_key": [
        {
          "current_key": "AIzaSyAmpy1-UoD2Aal1_7NQFmeSLzADHYsaVEA"
        }
      ],
      "services": {
        "analytics_service": {
          "status": 1
        },
        "appinvite_service": {
          "status": 1,
          "other_platform_oauth_client": []
        },
        "ads_service": {
          "status": 1
        }
      }
    }
  ],
  "configuration_version": "1"
}